DataRecorder/__init__.py
DataRecorder/base.py
DataRecorder/base.pyi
DataRecorder/byte_recorder.py
DataRecorder/byte_recorder.pyi
DataRecorder/db_recorder.py
DataRecorder/db_recorder.pyi
DataRecorder/filler.py
DataRecorder/filler.pyi
DataRecorder/recorder.py
DataRecorder/recorder.pyi
DataRecorder/setter.py
DataRecorder/setter.pyi
DataRecorder/tools.py
DataRecorder/tools.pyi
DataRecorder/style/__init__.py
DataRecorder/style/cell_style.py
DataRecorder-3.6.1.dist-info/LICENSE
DataRecorder-3.6.1.dist-info/METADATA
DataRecorder-3.6.1.dist-info/WHEEL
DataRecorder-3.6.1.dist-info/top_level.txt
DataRecorder-3.6.1.dist-info/RECORD
